setup.py
utilitybelt/__init__.py
utilitybelt/charsets.py
utilitybelt/dicts.py
utilitybelt/entropy.py
utilitybelt/numbers.py
utilitybelt.egg-info/PKG-INFO
utilitybelt.egg-info/SOURCES.txt
utilitybelt.egg-info/dependency_links.txt
utilitybelt.egg-info/not-zip-safe
utilitybelt.egg-info/top_level.txt