Metadata-Version: 1.1
Name: utilitybelt
Version: 0.1.7
Summary: Generally useful tools.
Home-page: https://github.com/onenameio/utilitybelt
Author: Halfmoon Labs
Author-email: hello@halfmoonlabs.com
License: MIT
Keywords: dict dictionary scrub to_dict todict json characters charset hex
Platform: UNKNOWN
Classifier: Intended Audience :: Developers
Classifier: License :: OSI Approved :: MIT License
Classifier: Operating System :: OS Independent
Classifier: Programming Language :: Python
